[
  {
    "id": "d388006a-6470-4ef8-b8c5-aa275790f8b0",
    "titulo": "Educação coorporativa",
    "responsavel": "Paulo",
    "data": "2025-02-19T00:00:00.000Z",
    "descricao": "Oficina de educação corporativa nas turmas de engenharia",
    "status": "Concluída"
  },
  {
    "id": "117dfb37-3879-41ea-ad8b-a3a17864fc44",
    "titulo": "Educação coorporativa",
    "responsavel": "Paulo",
    "data": "2025-02-26T00:00:00.000Z",
    "descricao": "Instalar PCs no laboratório",
    "status": "Pendente"
  },
  {
    "id": "aad04ad7-3db2-4cc3-847f-faffc42071d4",
    "titulo": "Zendaya - Replay",
    "responsavel": "Paulo",
    "data": "2025-02-28T00:00:00.000Z",
    "descricao": "Ouvir música",
    "status": "Em andamento"
  }
]